fotonower/__init__.py
fotonower-0.9.16.dist-info/DESCRIPTION.rst
fotonower-0.9.16.dist-info/LICENSE.txt
fotonower-0.9.16.dist-info/METADATA
fotonower-0.9.16.dist-info/RECORD
fotonower-0.9.16.dist-info/WHEEL
fotonower-0.9.16.dist-info/metadata.json
fotonower-0.9.16.dist-info/top_level.txt
